Metadata-Version: 1.0
Name: isaak-stat-distributions
Version: 0.1
Summary: Gaussian distributions
Home-page: UNKNOWN
Author: Isaak Kamau
Author-email: isaak2018@students.uonbi.ac.ke
License: UNKNOWN
Platform: UNKNOWN
